MANIFEST.in
README.md
README.rst
setup.cfg
setup.py
deckster/__init__.py
deckster/__version__.py
deckster/cl_utils.py
deckster/start.py
deckster/utKit.py
deckster.egg-info/PKG-INFO
deckster.egg-info/SOURCES.txt
deckster.egg-info/dependency_links.txt
deckster.egg-info/entry_points.txt
deckster.egg-info/not-zip-safe
deckster.egg-info/requires.txt
deckster.egg-info/top_level.txt
deckster/commonutils/__init__.py
deckster/commonutils/getpackagepath.py
deckster/tests/__init__.py
deckster/tests/test_start.py