Metadata-Version: 1.1
Name: deckster
Version: 0.2
Summary: CL tools to build a Reveal.js presentation from a single Multimarkdown file
Home-page: https://github.com/thespacedoctor/deckster
Author: David Young
Author-email: davidrobertyoung@gmail.com
License: MIT
Download-URL: https://github.com/thespacedoctor/deckster/archive/v0.2.zip
Keywords: markdown, presentation
Platform: UNKNOWN
Classifier: Development Status :: 4 - Beta
Classifier: License :: OSI Approved :: MIT License
Classifier: Programming Language :: Python :: 2.7
Classifier: Topic :: Utilities
